hrequire/__init__.py
hrequire/core.py
hrequire-1.0.2.dist-info/licenses/LICENSE
hrequire-1.0.2.dist-info/METADATA
hrequire-1.0.2.dist-info/WHEEL
hrequire-1.0.2.dist-info/entry_points.txt
hrequire-1.0.2.dist-info/top_level.txt
hrequire-1.0.2.dist-info/RECORD
