Metadata-Version: 2.4
Name: HRequire
Version: 1.0.2
Summary: Auto-generate requirements.txt from your Python project imports
Author-email: Thanaraklee <bzank.lee@hotmail.com>
License-Expression: MIT
Project-URL: Homepage, https://github.com/Thanaraklee/hrequire
Requires-Python: >=3.10
License-File: LICENSE
Dynamic: license-file
